{
  "name": "Dapur",
  "slug": "dapur",
  "children": [
    {
      "name": "Aksesoris Dapur",
      "slug": "dapur/aksesoris-dapur",
      "children": [
        {
          "name": "Alat Pemotong Serbaguna",
          "slug": "dapur/aksesoris-dapur/alat-pemotong-serbaguna",
          "children": []
        },
        {
          "name": "Capit Makanan",
          "slug": "dapur/aksesoris-dapur/capit-makanan",
          "children": []
        },
        {
          "name": "Celemek",
          "slug": "dapur/aksesoris-dapur/celemek",
          "children": []
        },
        {
          "name": "Chopper",
          "slug": "dapur/aksesoris-dapur/chopper",
          "children": []
        },
        {
          "name": "Grinder",
          "slug": "dapur/aksesoris-dapur/grinder",
          "children": []
        },
        {
          "name": "Gunting Dapur",
          "slug": "dapur/aksesoris-dapur/gunting-dapur",
          "children": []
        },
        {
          "name": "Korek Kompor",
          "slug": "dapur/aksesoris-dapur/korek-kompor",
          "children": []
        },
        {
          "name": "Magnet Kulkas",
          "slug": "dapur/aksesoris-dapur/magnet-kulkas",
          "children": []
        },
        {
          "name": "Parutan",
          "slug": "dapur/aksesoris-dapur/parutan",
          "children": []
        },
        {
          "name": "Peeler",
          "slug": "dapur/aksesoris-dapur/peeler",
          "children": []
        },
        {
          "name": "Pelindung Tangan",
          "slug": "dapur/aksesoris-dapur/pelindung-tangan",
          "children": []
        },
        {
          "name": "Pengasah Pisau",
          "slug": "dapur/aksesoris-dapur/pengasah-pisau",
          "children": []
        },
        {
          "name": "Pisau Dapur",
          "slug": "dapur/aksesoris-dapur/pisau-dapur",
          "children": []
        },
        {
          "name": "Pisau Set",
          "slug": "dapur/aksesoris-dapur/pisau-set",
          "children": []
        },
        {
          "name": "Talenan",
          "slug": "dapur/aksesoris-dapur/talenan",
          "children": []
        },
        {
          "name": "Tatakan Gas",
          "slug": "dapur/aksesoris-dapur/tatakan-gas",
          "children": []
        },
        {
          "name": "Termometer Makanan Minuman",
          "slug": "dapur/aksesoris-dapur/termometer-makanan-minuman",
          "children": []
        },
        {
          "name": "Timer Masak",
          "slug": "dapur/aksesoris-dapur/timer-masak",
          "children": []
        }
      ]
    },
    {
      "name": "Alat Masak Khusus",
      "slug": "dapur/alat-masak-khusus",
      "children": [
        {
          "name": "Chocolate Melter",
          "slug": "dapur/alat-masak-khusus/chocolate-melter",
          "children": []
        },
        {
          "name": "Coffee Tea Maker",
          "slug": "dapur/alat-masak-khusus/coffee-tea-maker",
          "children": []
        },
        {
          "name": "Cotton Candy Maker",
          "slug": "dapur/alat-masak-khusus/cotton-candy-maker",
          "children": []
        },
        {
          "name": "Donut Maker",
          "slug": "dapur/alat-masak-khusus/donut-maker",
          "children": []
        },
        {
          "name": "Ice Cream Yogurt Maker",
          "slug": "dapur/alat-masak-khusus/ice-cream-yogurt-maker",
          "children": []
        },
        {
          "name": "Mesin Es Serut",
          "slug": "dapur/alat-masak-khusus/mesin-es-serut",
          "children": []
        },
        {
          "name": "Mesin Sostel",
          "slug": "dapur/alat-masak-khusus/mesin-sostel",
          "children": []
        },
        {
          "name": "Noodle Pasta Maker",
          "slug": "dapur/alat-masak-khusus/noodle-pasta-maker",
          "children": []
        },
        {
          "name": "Pancake Maker",
          "slug": "dapur/alat-masak-khusus/pancake-maker",
          "children": []
        },
        {
          "name": "Popcorn Maker",
          "slug": "dapur/alat-masak-khusus/popcorn-maker",
          "children": []
        },
        {
          "name": "Sushi Maker Roller",
          "slug": "dapur/alat-masak-khusus/sushi-maker-roller",
          "children": []
        },
        {
          "name": "Waffle Maker",
          "slug": "dapur/alat-masak-khusus/waffle-maker",
          "children": []
        }
      ]
    },
    {
      "name": "Bekal",
      "slug": "dapur/bekal",
      "children": [
        {
          "name": "Botol Minum",
          "slug": "dapur/bekal/botol-minum",
          "children": []
        },
        {
          "name": "Cetakan Bento",
          "slug": "dapur/bekal/cetakan-bento",
          "children": []
        },
        {
          "name": "Cup Bento",
          "slug": "dapur/bekal/cup-bento",
          "children": []
        },
        {
          "name": "Kotak Makan",
          "slug": "dapur/bekal/kotak-makan",
          "children": []
        },
        {
          "name": "Lunch Box Set",
          "slug": "dapur/bekal/lunch-box-set",
          "children": []
        },
        {
          "name": "Partisi Bento",
          "slug": "dapur/bekal/partisi-bento",
          "children": []
        },
        {
          "name": "Rantang",
          "slug": "dapur/bekal/rantang",
          "children": []
        },
        {
          "name": "Tas Bekal",
          "slug": "dapur/bekal/tas-bekal",
          "children": []
        },
        {
          "name": "Tas Botol",
          "slug": "dapur/bekal/tas-botol",
          "children": []
        },
        {
          "name": "Termos Air",
          "slug": "dapur/bekal/termos-air",
          "children": []
        },
        {
          "name": "Tusuk Bento",
          "slug": "dapur/bekal/tusuk-bento",
          "children": []
        }
      ]
    },
    {
      "name": "Kemasan Makanan Dan Minuman",
      "slug": "dapur/kemasan-makanan-dan-minuman",
      "children": [
        {
          "name": "Aluminium Tray Cup",
          "slug": "dapur/kemasan-makanan-dan-minuman/aluminium-tray-cup",
          "children": []
        },
        {
          "name": "Bagasse",
          "slug": "dapur/kemasan-makanan-dan-minuman/bagasse",
          "children": []
        },
        {
          "name": "Bento Box",
          "slug": "dapur/kemasan-makanan-dan-minuman/bento-box",
          "children": []
        },
        {
          "name": "Box Kardus Makanan",
          "slug": "dapur/kemasan-makanan-dan-minuman/box-kardus-makanan",
          "children": []
        },
        {
          "name": "Box Mika",
          "slug": "dapur/kemasan-makanan-dan-minuman/box-mika",
          "children": []
        },
        {
          "name": "Food Pail",
          "slug": "dapur/kemasan-makanan-dan-minuman/food-pail",
          "children": []
        },
        {
          "name": "Food Paper Bag",
          "slug": "dapur/kemasan-makanan-dan-minuman/food-paper-bag",
          "children": []
        },
        {
          "name": "Kemasan Minuman",
          "slug": "dapur/kemasan-makanan-dan-minuman/kemasan-minuman",
          "children": []
        },
        {
          "name": "Paper Box",
          "slug": "dapur/kemasan-makanan-dan-minuman/paper-box",
          "children": []
        },
        {
          "name": "Paper Rice Bowl",
          "slug": "dapur/kemasan-makanan-dan-minuman/paper-rice-bowl",
          "children": []
        },
        {
          "name": "Thinwall",
          "slug": "dapur/kemasan-makanan-dan-minuman/thinwall",
          "children": []
        }
      ]
    },
    {
      "name": "Penyimpanan Makanan",
      "slug": "dapur/penyimpanan-makanan",
      "children": [
        {
          "name": "Aluminium Foil",
          "slug": "dapur/penyimpanan-makanan/aluminium-foil",
          "children": []
        },
        {
          "name": "Box Telur",
          "slug": "dapur/penyimpanan-makanan/box-telur",
          "children": []
        },
        {
          "name": "Cooler Box",
          "slug": "dapur/penyimpanan-makanan/cooler-box",
          "children": []
        },
        {
          "name": "Food Display",
          "slug": "dapur/penyimpanan-makanan/food-display",
          "children": []
        },
        {
          "name": "Food Warmer",
          "slug": "dapur/penyimpanan-makanan/food-warmer",
          "children": []
        },
        {
          "name": "Ice Rice Bucket",
          "slug": "dapur/penyimpanan-makanan/ice-rice-bucket",
          "children": []
        },
        {
          "name": "Plastic Wrap",
          "slug": "dapur/penyimpanan-makanan/plastic-wrap",
          "children": []
        },
        {
          "name": "Plastik Klip",
          "slug": "dapur/penyimpanan-makanan/plastik-klip",
          "children": []
        },
        {
          "name": "Sealer Makanan",
          "slug": "dapur/penyimpanan-makanan/sealer-makanan",
          "children": []
        },
        {
          "name": "Tempat Buah Sayur",
          "slug": "dapur/penyimpanan-makanan/tempat-buah-sayur",
          "children": []
        },
        {
          "name": "Tempat Bumbu",
          "slug": "dapur/penyimpanan-makanan/tempat-bumbu",
          "children": []
        },
        {
          "name": "Tempat Roti",
          "slug": "dapur/penyimpanan-makanan/tempat-roti",
          "children": []
        },
        {
          "name": "Tempat Saos Kecap",
          "slug": "dapur/penyimpanan-makanan/tempat-saos-kecap",
          "children": []
        },
        {
          "name": "Toples Makanan",
          "slug": "dapur/penyimpanan-makanan/toples-makanan",
          "children": []
        }
      ]
    },
    {
      "name": "Peralatan Baking",
      "slug": "dapur/peralatan-baking",
      "children": [
        {
          "name": "Alat Penghias Kue",
          "slug": "dapur/peralatan-baking/alat-penghias-kue",
          "children": []
        },
        {
          "name": "Cetakan Kue",
          "slug": "dapur/peralatan-baking/cetakan-kue",
          "children": []
        },
        {
          "name": "Kertas Baking",
          "slug": "dapur/peralatan-baking/kertas-baking",
          "children": []
        },
        {
          "name": "Kocokan Telur",
          "slug": "dapur/peralatan-baking/kocokan-telur",
          "children": []
        },
        {
          "name": "Kuas Kue",
          "slug": "dapur/peralatan-baking/kuas-kue",
          "children": []
        },
        {
          "name": "Loyang Kue",
          "slug": "dapur/peralatan-baking/loyang-kue",
          "children": []
        },
        {
          "name": "Pisau Kue",
          "slug": "dapur/peralatan-baking/pisau-kue",
          "children": []
        },
        {
          "name": "Tatakan Kue",
          "slug": "dapur/peralatan-baking/tatakan-kue",
          "children": []
        }
      ]
    },
    {
      "name": "Peralatan Dapur",
      "slug": "dapur/peralatan-dapur",
      "children": [
        {
          "name": "Alat Pembuka Botol",
          "slug": "dapur/peralatan-dapur/alat-pembuka-botol",
          "children": []
        },
        {
          "name": "Alat Pembuka Kaleng",
          "slug": "dapur/peralatan-dapur/alat-pembuka-kaleng",
          "children": []
        },
        {
          "name": "Dispenser Air",
          "slug": "dapur/peralatan-dapur/dispenser-air",
          "children": []
        },
        {
          "name": "Pompa Galon",
          "slug": "dapur/peralatan-dapur/pompa-galon",
          "children": []
        },
        {
          "name": "Rak Dapur",
          "slug": "dapur/peralatan-dapur/rak-dapur",
          "children": []
        },
        {
          "name": "Rak Piring Gelas",
          "slug": "dapur/peralatan-dapur/rak-piring-gelas",
          "children": []
        },
        {
          "name": "Regulator Penghemat Gas",
          "slug": "dapur/peralatan-dapur/regulator-penghemat-gas",
          "children": []
        },
        {
          "name": "Sarung Galon",
          "slug": "dapur/peralatan-dapur/sarung-galon",
          "children": []
        },
        {
          "name": "Sarung Kulkas",
          "slug": "dapur/peralatan-dapur/sarung-kulkas",
          "children": []
        },
        {
          "name": "Timbangan Dapur",
          "slug": "dapur/peralatan-dapur/timbangan-dapur",
          "children": []
        },
        {
          "name": "Water Purifier",
          "slug": "dapur/peralatan-dapur/water-purifier",
          "children": []
        }
      ]
    },
    {
      "name": "Peralatan Makan Minum",
      "slug": "dapur/peralatan-makan-minum",
      "children": [
        {
          "name": "Cangkir",
          "slug": "dapur/peralatan-makan-minum/cangkir",
          "children": []
        },
        {
          "name": "Centong Nasi",
          "slug": "dapur/peralatan-makan-minum/centong-nasi",
          "children": []
        },
        {
          "name": "Gelas Mug",
          "slug": "dapur/peralatan-makan-minum/gelas-mug",
          "children": []
        },
        {
          "name": "Gelas Wine",
          "slug": "dapur/peralatan-makan-minum/gelas-wine",
          "children": []
        },
        {
          "name": "Mangkok Makan",
          "slug": "dapur/peralatan-makan-minum/mangkok-makan",
          "children": []
        },
        {
          "name": "Nampan",
          "slug": "dapur/peralatan-makan-minum/nampan",
          "children": []
        },
        {
          "name": "Paket Peralatan Makan",
          "slug": "dapur/peralatan-makan-minum/paket-peralatan-makan",
          "children": []
        },
        {
          "name": "Paket Peralatan Minum",
          "slug": "dapur/peralatan-makan-minum/paket-peralatan-minum",
          "children": []
        },
        {
          "name": "Piring Mangkok Saji",
          "slug": "dapur/peralatan-makan-minum/piring-mangkok-saji",
          "children": []
        },
        {
          "name": "Piring Makan",
          "slug": "dapur/peralatan-makan-minum/piring-makan",
          "children": []
        },
        {
          "name": "Pitcher Minuman",
          "slug": "dapur/peralatan-makan-minum/pitcher-minuman",
          "children": []
        },
        {
          "name": "Sedotan",
          "slug": "dapur/peralatan-makan-minum/sedotan",
          "children": []
        },
        {
          "name": "Sendok Garpu Dessert",
          "slug": "dapur/peralatan-makan-minum/sendok-garpu-dessert",
          "children": []
        },
        {
          "name": "Sendok Garpu Makan",
          "slug": "dapur/peralatan-makan-minum/sendok-garpu-makan",
          "children": []
        },
        {
          "name": "Sendok Bebek",
          "slug": "dapur/peralatan-makan-minum/sendok-bebek",
          "children": []
        },
        {
          "name": "Sendok Sayur Kuah",
          "slug": "dapur/peralatan-makan-minum/sendok-sayur-kuah",
          "children": []
        },
        {
          "name": "Sumpit",
          "slug": "dapur/peralatan-makan-minum/sumpit",
          "children": []
        },
        {
          "name": "Sumpit Makan",
          "slug": "dapur/peralatan-makan-minum/sumpit-makan",
          "children": []
        },
        {
          "name": "Tatakan Gelas Piring",
          "slug": "dapur/peralatan-makan-minum/tatakan-gelas-piring",
          "children": []
        },
        {
          "name": "Tempat Sendok Garpu",
          "slug": "dapur/peralatan-makan-minum/tempat-sendok-garpu",
          "children": []
        },
        {
          "name": "Tudung Saji",
          "slug": "dapur/peralatan-makan-minum/tudung-saji",
          "children": []
        },
        {
          "name": "Tutup Gelas Piring",
          "slug": "dapur/peralatan-makan-minum/tutup-gelas-piring",
          "children": []
        }
      ]
    },
    {
      "name": "Peralatan Masak",
      "slug": "dapur/peralatan-masak",
      "children": [
        {
          "name": "Cetakan Es Puding Coklat",
          "slug": "dapur/peralatan-masak/cetakan-es-puding-coklat",
          "children": []
        },
        {
          "name": "Cobek",
          "slug": "dapur/peralatan-masak/cobek",
          "children": []
        },
        {
          "name": "Deep Fryer",
          "slug": "dapur/peralatan-masak/deep-fryer",
          "children": []
        },
        {
          "name": "Gelas Takar",
          "slug": "dapur/peralatan-masak/gelas-takar",
          "children": []
        },
        {
          "name": "Gilingan Daging",
          "slug": "dapur/peralatan-masak/gilingan-daging",
          "children": []
        },
        {
          "name": "Griller",
          "slug": "dapur/peralatan-masak/griller",
          "children": []
        },
        {
          "name": "Kompor",
          "slug": "dapur/peralatan-masak/kompor",
          "children": []
        },
        {
          "name": "Oven Gas",
          "slug": "dapur/peralatan-masak/oven-gas",
          "children": []
        },
        {
          "name": "Panci",
          "slug": "dapur/peralatan-masak/panci",
          "children": []
        },
        {
          "name": "Presto",
          "slug": "dapur/peralatan-masak/presto",
          "children": []
        },
        {
          "name": "Saringan Masak",
          "slug": "dapur/peralatan-masak/saringan-masak",
          "children": []
        },
        {
          "name": "Sendok Takar",
          "slug": "dapur/peralatan-masak/sendok-takar",
          "children": []
        },
        {
          "name": "Spatula Sutil",
          "slug": "dapur/peralatan-masak/spatula-sutil",
          "children": []
        },
        {
          "name": "Steamer",
          "slug": "dapur/peralatan-masak/steamer",
          "children": []
        },
        {
          "name": "Teko Pemanas Air",
          "slug": "dapur/peralatan-masak/teko-pemanas-air",
          "children": []
        },
        {
          "name": "Wajan",
          "slug": "dapur/peralatan-masak/wajan",
          "children": []
        }
      ]
    },
    {
      "name": "Perlengkapan Cuci Piring",
      "slug": "dapur/perlengkapan-cuci-piring",
      "children": [
        {
          "name": "Dish Dryer",
          "slug": "dapur/perlengkapan-cuci-piring/dish-dryer",
          "children": []
        },
        {
          "name": "Sabut",
          "slug": "dapur/perlengkapan-cuci-piring/sabut",
          "children": []
        },
        {
          "name": "Saringan Bak Cuci Piring",
          "slug": "dapur/perlengkapan-cuci-piring/saringan-bak-cuci-piring",
          "children": []
        },
        {
          "name": "Sikat Cuci Botol",
          "slug": "dapur/perlengkapan-cuci-piring/sikat-cuci-botol",
          "children": []
        },
        {
          "name": "Sponge Cuci Piring",
          "slug": "dapur/perlengkapan-cuci-piring/sponge-cuci-piring",
          "children": []
        }
      ]
    }
  ]
}